{
    "manifest": {
        "author": "HellsAdramelech",
        "version": "1.0.0",
        "name": "Wendsday",
        "updater": "https:\/\/raw.githubusercontent.com\/Hellsadramelech\/Aliucord\/main\/Themes\/Wendsday\/Wensday.json"
    },
    "background": "https:\/\/github.com\/Hellsadramelech\/Aliucord\/blob\/main\/Themes\/Wendsday\/Background\/Wendsday.png"
    },
    "fonts": {
        "*": "https:\/\/cdn.discordapp.com\/attachments\/784158474761273374\/961678009218265249\/Comfortaa-Bold.ttf"
    },
    "simple_colors": {
        "background": -15004610,
        "background_secondary": -15398351,
        "mention_highlight": -14217377,
        "active_channel": -14151583,
        "statusbar": -15004610,
        "input_background": -14151583,
        "blocked_bg": -15399370,
        "accent": -5994770
    },
    "colors": {
        "brand_new_360": -13631326,
        "link_500": -5994770,
        "brand_new_900": -16777216,
        "primary_dark_100": -13107007,
        "primary_dark_300": -5994770,
        "primary_dark_400": -5994770,
        "primary_630": -15004610,
        "primary_660": -1,
        "primary_700_alpha_60": -5994770,
        "white_500": -2372353,
        "white_800": -16777216,
        "primary_600": -5994770,
        "uikit_btn_bg_color_selector_green": -5994770,
        "uikit_btn_bg_color_selector_red": -5994770,
        "uikit_settings_item_text_color_light": -12635549,
        "primary_dark_660": -13623969,
        "primary_dark_800": -15398351,
        "dim_foreground_material_light": -14873022,
        "transparent": 0,
        "primary_dark_360": -6781244,
        "primary_dark_330": -5994770
    },
    "drawable_tints": {
        "drawable_button_grey": -5994770,
        "ic_sidebar_notifications_off_dark_24dp": -5994770,
        "ic_sidebar_notifications_on_dark_24dp": -5994770,
        "ic_channel_topic_ellipsis_dark": -16777216,
        "ic_guild_notifications_24dp": -5994770,
        "ic_sidebar_pins_on_dark_24dp": -5994770,
        "ic_sidebar_pins_off_dark_24dp": -5994770,
        "ic_content_copy_white_a60_24dp": -2372353,
        "ic_channel_announcements_thread_locked": -12700584,
        "ic_channel_lock_16dp": -2372353,
        "ic_channel_text_nsfw": -2372353,
        "ic_channel_text_locked": -2372353,
        "ic_channel_announcements": -2372353,
        "ic_channel_announcements_locked": -2372353,
        "ic_channel_announcements_nsfw": -2372353,
        "ic_channel_announcements_thread": -2372353,
        "ic_channel_announcements_thread_nsfw": -2372353,
        "ic_channel_stage_16dp": -2372353,
        "ic_notifications_settings_white_a60_24dp": -2372353,
        "ic_account_circle_white_a60_24dp": -2372353,
        "ic_thread_white_24dp": -2372353,
        "ic_visibility_white_24dp": -2372353,
        "ic_thread": -5994770,
        "ic_guild_invite_24dp": -5994770,
        "ic_call_invite_icon": -5994770,
        "ic_edit_24dp": -5994770,
        "ic_guild_settings_24dp": -5994770,
        "ic_settings_24dp": -5994770,
        "ic_settings_white_a60_24dp": -2372353,
        "ic_add_friend_plus": -5994770,
        "ic_header_members_add_white_24dp": -5994770,
        "ic_person_add_white_a60_24dp": -2372353,
        "ic_user_profile_action_call_white_24dp": -5994770,
        "ic_user_profile_action_message_white_a60_24dp": -5994770,
        "ic_user_profile_action_video_white_a60_24dp": -5994770,
        "ic_mobile": -5994770,
        "ic_user_profile_action_call_white_a60_24dp": -5994770,
        "ic_user_actions_block_white_a60_24dp": -9620737,
        "ic_user_actions_remove_friend_white_a60_24dp": -9620737,
        "ic_user_actions_unblock_white_a60_24dp": -5994770,
        "ic_user_profile_action_call_grey_a60_24dp": -5994770,
        "ic_user_profile_action_message_grey_a60_24dp": -5994770,
        "ic_user_profile_action_video_grey_a60_24dp": -5994770,
        "ic_channel_pinned_message": -2372353,
        "ic_channel_text_grey_a60_24dp": -2372353,
        "ic_channel_text_grey_18dp": -2372353,
        "ic_channel_text_16dp": -2372353,
        "ic_channel_text_white_a60_24dp": -2372353,
        "ic_text_channel_white_24dp": -2372353,
        "ic_status_idle_16dp": -175769634,
        "ic_archived_clock_dark": -2372353,
        "ic_chat_message_white_24dp": -2372353,
        "ic_chat_list_actions_add_reaction": -2372353,
        "ic_chat_message_16dp": -2372353,
        "ic_settings_grey_a60_24dp": -2372353,
        "img_empty_server_settings_invites_dark": -2372353,
        "drawable_bg_loading": -2372353,
        "ic_add_circle": -2372353,
        "ic_add_person_16dp": -2372353,
        "ic_group_add_white_24dp": -2372353,
        "ic_image_upload_padding": -2372353,
        "img_discord_nitro_logo_left": -2372353,
        "img_logo_discord": -2372353,
        "img_logo_discord_nitro": -2372353,
        "img_logo_discord_nitro_and_boost": -2372353,
        "img_logo_discord_nitro_and_boost_horizontal": -2372353,
        "img_logo_discord_nitro_classic": -2372353
    },
    "raws": {}
}
